{"nodes": [{"id": "whatsapp_page", "label": "WhatsApp Page", "file_type": "document", "source_file": "docs/whatsapp-page.md"}, {"id": "whatsapp_conversations", "label": "whatsapp_conversations", "file_type": "code", "source_file": "docs/whatsapp-page.md"}, {"id": "whatsapp_messages", "label": "whatsapp_messages", "file_type": "code", "source_file": "docs/whatsapp-page.md"}], "edges": [{"source": "whatsapp_conversations", "target": "leads_table", "relation": "references", "confidence": "EXTRACTED", "confidence_score": 1.0, "source_file": "docs/whatsapp-page.md"}, {"source": "whatsapp_messages", "target": "whatsapp_conversations", "relation": "references", "confidence": "EXTRACTED", "confidence_score": 1.0, "source_file": "docs/whatsapp-page.md"}], "hyperedges": []}